qiskit2quafu/__init__.py
qiskit2quafu-0.0.15.dist-info/LICENSE
qiskit2quafu-0.0.15.dist-info/METADATA
qiskit2quafu-0.0.15.dist-info/WHEEL
qiskit2quafu-0.0.15.dist-info/top_level.txt
qiskit2quafu-0.0.15.dist-info/RECORD
