Metadata-Version: 2.1
Name: qiskit2quafu
Version: 0.0.15
Summary: This package converts the circuit of qiskit into a circuit supported by quafu
Home-page: https://github.com/ladium493/qiskit2quafu
Author: XR Wang
Author-email: wang.x.aw@m.titech.ac.jp
License: MIT
Classifier: Programming Language :: Python :: 3
Classifier: License :: OSI Approved :: MIT License
Classifier: Operating System :: OS Independent
Requires-Python: >=3.6
License-File: LICENSE
Requires-Dist: qiskit
Requires-Dist: pyquafu
